MANIFEST.in
setup.py
procboy/__init__.py
procboy/boy.py
procboy.egg-info/PKG-INFO
procboy.egg-info/SOURCES.txt
procboy.egg-info/dependency_links.txt
procboy.egg-info/entry_points.txt
procboy.egg-info/requires.txt
procboy.egg-info/top_level.txt
procboy/utils/__init__.py
procboy/utils/runner.py