Metadata-Version: 1.0
Name: procboy
Version: 0.1.6
Summary: ProcBoy - Manage processes
Home-page: http://github.com/futurice/procboy
Author: Jussi Vaihia
Author-email: jussi.vaihia@futurice.com
License: BSD
Keywords: process procboy processboy
Platform: UNKNOWN
